eazyrent_sdk/__init__.py
eazyrent_sdk/api/__init__.py
eazyrent_sdk/api/eazyrent_sdk.py
eazyrent_sdk/api/namespaces/__init__.py
eazyrent_sdk/api/namespaces/actions/__init__.py
eazyrent_sdk/api/namespaces/alerts/__init__.py
eazyrent_sdk/api/namespaces/alerts/datetimes/__init__.py
eazyrent_sdk/api/namespaces/alerts/datetimes/main.py
eazyrent_sdk/api/namespaces/alerts/externals/__init__.py
eazyrent_sdk/api/namespaces/alerts/externals/companies.py
eazyrent_sdk/api/namespaces/alerts/externals/main.py
eazyrent_sdk/api/namespaces/alerts/externals/tax_notices.py
eazyrent_sdk/api/namespaces/alerts/main.py
eazyrent_sdk/api/namespaces/alerts/mrz/__init__.py
eazyrent_sdk/api/namespaces/alerts/strings/__init__.py
eazyrent_sdk/api/namespaces/alerts/strings/main.py
eazyrent_sdk/api/namespaces/alerts/tabular_data/__init__.py
eazyrent_sdk/interfaces/__init__.py
eazyrent_sdk/interfaces/alerts.py
eazyrent_sdk/interfaces/applicants.py
eazyrent_sdk/interfaces/context.py
eazyrent_sdk/interfaces/documents.py
eazyrent_sdk/interfaces/rental_files.py
eazyrent_sdk/interfaces/types.py
eazyrent_sdk/tests/__init__.py
eazyrent_sdk/tests/api/__init__.py
eazyrent_sdk/tests/api/test_alert_sdk.py
eazyrent_sdk/tests/conftest.py
eazyrent_sdk-0.0.1.dist-info/LICENSE.md
eazyrent_sdk-0.0.1.dist-info/METADATA
eazyrent_sdk-0.0.1.dist-info/WHEEL
eazyrent_sdk-0.0.1.dist-info/RECORD
